treedump/__init__.py
treedump/cli.py
treedump-0.2.0.dist-info/licenses/LICENSE
treedump-0.2.0.dist-info/METADATA
treedump-0.2.0.dist-info/WHEEL
treedump-0.2.0.dist-info/entry_points.txt
treedump-0.2.0.dist-info/top_level.txt
treedump-0.2.0.dist-info/RECORD
