Metadata-Version: 2.4
Name: treedump
Version: 0.2.0
Summary: Dump all text files in a directory tree into a single file
Author: appfeat
Requires-Python: >=3.9
License-File: LICENSE
Dynamic: license-file
